foundry_dev_tools-2.1.22.dist-info/METADATA
foundry_dev_tools-2.1.22.dist-info/WHEEL
foundry_dev_tools-2.1.22.dist-info/entry_points.txt
foundry_dev_tools/__about__.py
foundry_dev_tools/__init__.py
foundry_dev_tools/_optional/__init__.py
foundry_dev_tools/_optional/foundry_platform_sdk.py
foundry_dev_tools/_optional/pandas.py
foundry_dev_tools/_optional/polars.py
foundry_dev_tools/_optional/pyarrow.py
foundry_dev_tools/_optional/pyspark.py
foundry_dev_tools/cached_foundry_client.py
foundry_dev_tools/cli/__init__.py
foundry_dev_tools/cli/build.py
foundry_dev_tools/cli/config.py
foundry_dev_tools/cli/git.py
foundry_dev_tools/cli/git_credential_foundry.py
foundry_dev_tools/cli/info.py
foundry_dev_tools/cli/main.py
foundry_dev_tools/cli/s3.py
foundry_dev_tools/cli/stubs.py
foundry_dev_tools/clients/__init__.py
foundry_dev_tools/clients/api_client.py
foundry_dev_tools/clients/build2.py
foundry_dev_tools/clients/catalog.py
foundry_dev_tools/clients/compass.py
foundry_dev_tools/clients/context_client.py
foundry_dev_tools/clients/data_health.py
foundry_dev_tools/clients/data_proxy.py
foundry_dev_tools/clients/foundry_sql_server.py
foundry_dev_tools/clients/foundry_stats.py
foundry_dev_tools/clients/jemma.py
foundry_dev_tools/clients/magritte_coordinator.py
foundry_dev_tools/clients/metadata.py
foundry_dev_tools/clients/multipass.py
foundry_dev_tools/clients/public_ontologies_client.py
foundry_dev_tools/clients/s3_client.py
foundry_dev_tools/clients/scheduler.py
foundry_dev_tools/clients/schema_inference.py
foundry_dev_tools/clients/tables.py
foundry_dev_tools/config/__init__.py
foundry_dev_tools/config/config.py
foundry_dev_tools/config/config_types.py
foundry_dev_tools/config/context.py
foundry_dev_tools/config/token_provider.py
foundry_dev_tools/errors/__init__.py
foundry_dev_tools/errors/compass.py
foundry_dev_tools/errors/config.py
foundry_dev_tools/errors/dataset.py
foundry_dev_tools/errors/handling.py
foundry_dev_tools/errors/meta.py
foundry_dev_tools/errors/multipass.py
foundry_dev_tools/errors/sql.py
foundry_dev_tools/foundry_api_client.py
foundry_dev_tools/helpers/__init__.py
foundry_dev_tools-2.1.22.dist-info/RECORD
